dataupdater/__init__.py
dataupdater/core.py
dataupdater-0.1.6.dist-info/licenses/LICENSE
dataupdater-0.1.6.dist-info/METADATA
dataupdater-0.1.6.dist-info/WHEEL
dataupdater-0.1.6.dist-info/top_level.txt
dataupdater-0.1.6.dist-info/RECORD
