Metadata-Version: 2.4
Name: dataupdater
Version: 0.1.6
Summary: A live Python variable editor via web interface
Author: Anson Wong
Author-email: Anson <ansonwong815@gmail.com>
License: MIT
Requires-Python: >=3.7
License-File: LICENSE
Dynamic: author
Dynamic: license-file
